jetblack_fincal/__init__.py
jetblack_fincal/belgium.py
jetblack_fincal/germany.py
jetblack_fincal/ice.py
jetblack_fincal/netherlands.py
jetblack_fincal/nyse.py
jetblack_fincal/py.typed
jetblack_fincal/target.py
jetblack_fincal/trayport.py
jetblack_fincal/uk.py
jetblack_fincal-0.1.0.dist-info/WHEEL
jetblack_fincal-0.1.0.dist-info/METADATA
jetblack_fincal-0.1.0.dist-info/RECORD
